{
  "mainAssemblyName": "qr.dll",
  "assemblyRootFolder": "managed",
  "debugLevel": -1,
  "assets": [
    {
      "behavior": "assembly",
      "name": "dotnet-wasm-react/qr.dll"
    },
    {
      "behavior": "assembly",
      "name": "dotnet-wasm-react/qr.pdb"
    },
    {
      "behavior": "assembly",
      "name": "dotnet-wasm-react/QRCoder.dll"
    },
    {
      "behavior": "assembly",
      "name": "dotnet-wasm-react/System.Collections.Concurrent.dll"
    },
    {
      "behavior": "assembly",
      "name": "dotnet-wasm-react/System.Collections.dll"
    },
    {
      "behavior": "assembly",
      "name": "dotnet-wasm-react/System.Console.dll"
    },
    {
      "behavior": "assembly",
      "name": "dotnet-wasm-react/System.IO.Compression.dll"
    },
    {
      "behavior": "assembly",
      "name": "dotnet-wasm-react/System.Linq.dll"
    },
    {
      "behavior": "assembly",
      "name": "dotnet-wasm-react/System.Private.CoreLib.dll"
    },
    {
      "behavior": "assembly",
      "name": "dotnet-wasm-react/System.Private.Uri.dll"
    },
    {
      "behavior": "assembly",
      "name": "dotnet-wasm-react/System.Runtime.dll"
    },
    {
      "behavior": "assembly",
      "name": "dotnet-wasm-react/System.Runtime.InteropServices.dll"
    },
    {
      "behavior": "assembly",
      "name": "dotnet-wasm-react/System.Runtime.InteropServices.JavaScript.dll"
    },
    {
      "behavior": "assembly",
      "name": "dotnet-wasm-react/System.Text.Encoding.CodePages.dll"
    },
    {
      "behavior": "assembly",
      "name": "dotnet-wasm-react/System.Text.RegularExpressions.dll"
    },
    {
      "virtualPath": "runtimeconfig.bin",
      "behavior": "vfs",
      "name": "dotnet-wasm-react/supportFiles/0_runtimeconfig.bin"
    },
    {
      "virtualPath": "dotnet.js.symbols",
      "behavior": "vfs",
      "name": "dotnet-wasm-react/supportFiles/1_dotnet.js.symbols"
    },
    {
      "loadRemote": false,
      "behavior": "icu",
      "name": "dotnet-wasm-react/icudt.dat"
    },
    {
      "virtualPath": "/usr/share/zoneinfo/",
      "behavior": "vfs",
      "name": "dotnet-wasm-react/dotnet.timezones.blat"
    },
    {
      "behavior": "dotnetwasm",
      "name": "dotnet-wasm-react/dotnet.wasm"
    }
  ],
  "remoteSources": [],
  "pthreadPoolSize": 0
}